<xml xmlns:o="urn:schemas-microsoft-com:office:office">
 <o:MainFile HRef="../index.html"/>
 <o:File HRef="image294.jpg"/>
 <o:File HRef="image296.jpg"/>
 <o:File HRef="image2961.jpg"/>
 <o:File HRef="image311.gif"/>
 <o:File HRef="image300.png"/>
 <o:File HRef="image3001.jpg"/>
 <o:File HRef="image331.png"/>
 <o:File HRef="image3311.jpg"/>
 <o:File HRef="image323.png"/>
 <o:File HRef="image3231.jpg"/>
 <o:File HRef="image334.png"/>
 <o:File HRef="image3341.jpg"/>
 <o:File HRef="image304.png"/>
 <o:File HRef="image3041.jpg"/>
 <o:File HRef="filelist.xml"/>
</xml>